imagenetscraper.py
imagenetscraper-1.0.2.dist-info/LICENSE.txt
imagenetscraper-1.0.2.dist-info/METADATA
imagenetscraper-1.0.2.dist-info/WHEEL
imagenetscraper-1.0.2.dist-info/entry_points.txt
imagenetscraper-1.0.2.dist-info/top_level.txt
imagenetscraper-1.0.2.dist-info/RECORD
