Metadata-Version: 2.1
Name: imagenetscraper
Version: 1.0.2
Summary: Bulk-download all thumbnails from an ImageNet synset, with optional rescaling
Home-page: https://github.com/spinda/imagenetscraper
Author: Michael Smith
Author-email: michael@spinda.net
License: AGPLv3
Download-URL: https://github.com/spinda/imagenetscraper/archive/1.0.2.tar.gz
Keywords: imagenet,synset,scraper,download,ml
Platform: UNKNOWN
Requires-Dist: click
Requires-Dist: defusedxml
Requires-Dist: frogress
Requires-Dist: grequests
Requires-Dist: pillow
Requires-Dist: requests
